README.md
flask_common.py
setup.py
Flask_Common.egg-info/PKG-INFO
Flask_Common.egg-info/SOURCES.txt
Flask_Common.egg-info/dependency_links.txt
Flask_Common.egg-info/not-zip-safe
Flask_Common.egg-info/requires.txt
Flask_Common.egg-info/top_level.txt