Metadata-Version: 1.1
Name: Flask-Common
Version: 0.3.0
Summary: A Flask extension with lots of common time-savers (file-serving, favicons, etc).
Home-page: https://github.com/kennethreitz/flask-common
Author: Kenneth Reitz
Author-email: me@kennethreitz.org
License: BSD
Platform: any
Classifier: Environment :: Web Environment
Classifier: Intended Audience :: Developers
Classifier: License :: OSI Approved :: BSD License
Classifier: Operating System :: OS Independent
Classifier: Programming Language :: Python
Classifier: Topic :: Internet :: WWW/HTTP :: Dynamic Content
Classifier: Topic :: Software Development :: Libraries :: Python Modules
